{
  "tree_name": "NTU",
  "detectors": {
    "crilin": {
      "_comment": "null active_ch_list means all channels active",
      "active_ch_list": [3, 4],
      "to_be_inverted": false,
      "map_filename": "maps/laser_2ch.csv",
      "waves_branch_name": "Waves",
      "reco_conf": {
        "signal_samples_pre_peak": 25,
        "signal_samples_post_peak": 500,
        "charge_zerosup_peak_threshold": 10,
        "rise_samples_pre_peak": 20,
        "rise_samples_post_peak": 20,
        "sampling_rate": 5,
        "cf": 0.12,
        "interpolation_factor": 20,
        "do_centroid": true,
        "do_timing": true
      }
    }
  }
}
